dimwit/__init__.py
dimwit/air_pollution.py
dimwit/airflow.py
dimwit/legacy.py
dimwit/main.py
dimwit/pomodoro.py
dimwit/sleep.py
dimwit/weight.py
dimwit-0.3.2.dist-info/METADATA
dimwit-0.3.2.dist-info/WHEEL
dimwit-0.3.2.dist-info/top_level.txt
dimwit-0.3.2.dist-info/RECORD
