Metadata-Version: 2.4
Name: dimwit
Version: 0.3.2
Summary: A package containing various functions and classes for fetching, transforming, and visualising data for personal metrics.
Author-email: Daniel Soutar <danielsoutar144@gmail.com>
Project-URL: repository, https://github.com/danielsoutar/dimwit
Requires-Python: <4.0,>=3.10
Requires-Dist: jupyter>=1.1.1
Requires-Dist: matplotlib>=3.10.1
Requires-Dist: pandas>=2.2.3
Requires-Dist: requests>=2.32.3
Requires-Dist: scipy>=1.15.2
Requires-Dist: seaborn>=0.13.2
Requires-Dist: shapely>=2.0.7
Requires-Dist: tqdm>=4.67.1
